{"name":"Paradigm","className":"DataModel","filePaths":["default.project.json"],"children":[{"name":"ReplicatedStorage","className":"ReplicatedStorage","children":[{"name":"Components","className":"Folder","filePaths":["src/ReplicatedStorage\\Components\\init.meta.json"],"children":[{"name":"PlayerComponent","className":"ModuleScript","filePaths":["src/ReplicatedStorage\\Components\\PlayerComponent\\init.lua"],"children":[{"name":"ActionComponent","className":"ModuleScript","filePaths":["src/ReplicatedStorage\\Components\\PlayerComponent\\ActionComponent\\init.lua"],"children":[{"name":"Contexts","className":"ModuleScript","filePaths":["src/ReplicatedStorage\\Components\\PlayerComponent\\ActionComponent\\Contexts.lua"]}]},{"name":"GameComponent","className":"ModuleScript","filePaths":["src/ReplicatedStorage\\Components\\PlayerComponent\\GameComponent.lua"]},{"name":"PlayerEffects","className":"ModuleScript","filePaths":["src/ReplicatedStorage\\Components\\PlayerComponent\\PlayerEffects.lua"]},{"name":"TowersComponent","className":"ModuleScript","filePaths":["src/ReplicatedStorage\\Components\\PlayerComponent\\TowersComponent.lua"]}]},{"name":"ReplicationComponent","className":"ModuleScript","filePaths":["src/ReplicatedStorage\\Components\\ReplicationComponent.lua"]},{"name":"SignalComponent","className":"ModuleScript","filePaths":["src/ReplicatedStorage\\Components\\SignalComponent\\init.lua"],"children":[{"name":"CustomFunctions","className":"ModuleScript","filePaths":["src/ReplicatedStorage\\Components\\SignalComponent\\CustomFunctions.lua"]},{"name":"DataTransfer","className":"ModuleScript","filePaths":["src/ReplicatedStorage\\Components\\SignalComponent\\DataTransfer.lua"]},{"name":"PackageComponent","className":"ModuleScript","filePaths":["src/ReplicatedStorage\\Components\\SignalComponent\\PackageComponent.lua"]}]}]},{"name":"Info","className":"Folder","filePaths":["src/ReplicatedStorage\\Info\\init.meta.json"],"children":[{"name":"EnemiesInfo","className":"ModuleScript","filePaths":["src/ReplicatedStorage\\Info\\EnemiesInfo.lua"]},{"name":"Games","className":"Folder","filePaths":["src/ReplicatedStorage\\Info\\Games\\init.meta.json"],"children":[{"name":"TestGame","className":"ModuleScript","filePaths":["src/ReplicatedStorage\\Info\\Games\\TestGame.lua"]}]},{"name":"GlobalInfo","className":"ModuleScript","filePaths":["src/ReplicatedStorage\\Info\\GlobalInfo.lua"]},{"name":"Towers","className":"Folder","filePaths":["src/ReplicatedStorage\\Info\\Towers\\init.meta.json"],"children":[{"name":"Mine","className":"ModuleScript","filePaths":["src/ReplicatedStorage\\Info\\Towers\\Mine.lua"]},{"name":"MovingPrecursor","className":"ModuleScript","filePaths":["src/ReplicatedStorage\\Info\\Towers\\MovingPrecursor.lua"]},{"name":"Precursor","className":"ModuleScript","filePaths":["src/ReplicatedStorage\\Info\\Towers\\Precursor.lua"]}]}]},{"name":"MadworkMaid","className":"ModuleScript","filePaths":["src/ReplicatedStorage\\MadworkMaid.lua"]},{"name":"MadworkScriptSignal","className":"ModuleScript","filePaths":["src/ReplicatedStorage\\MadworkScriptSignal.lua"]},{"name":"RateLimiter","className":"ModuleScript","filePaths":["src/ReplicatedStorage\\RateLimiter.lua"]},{"name":"ReplicaController","className":"ModuleScript","filePaths":["src/ReplicatedStorage\\ReplicaController.lua"]},{"name":"Replication","className":"Folder","filePaths":["src/ReplicatedStorage\\Replication\\init.meta.json"],"children":[{"name":"Effects","className":"Folder","children":[{"name":"TestEffects","className":"ModuleScript","filePaths":["src/ReplicatedStorage\\Replication\\Effects\\TestEffects.lua"]}]},{"name":"EnemiesEffects","className":"ModuleScript","filePaths":["src/ReplicatedStorage\\Replication\\EnemiesEffects.lua"]},{"name":"EntitiesEffects","className":"ModuleScript","filePaths":["src/ReplicatedStorage\\Replication\\EntitiesEffects.lua"]},{"name":"TowersEffects","className":"ModuleScript","filePaths":["src/ReplicatedStorage\\Replication\\TowersEffects.lua"]}]},{"name":"StudioExecutor","className":"Script","filePaths":["src/ReplicatedStorage\\StudioExecutor.server.lua"]},{"name":"Templates","className":"Folder","filePaths":["src/ReplicatedStorage\\Templates\\init.meta.json"],"children":[{"name":"EnemyTemplate","className":"ModuleScript","filePaths":["src/ReplicatedStorage\\Templates\\EnemyTemplate.lua"]},{"name":"EntityTemplate","className":"ModuleScript","filePaths":["src/ReplicatedStorage\\Templates\\EntityTemplate.lua"]},{"name":"Enums","className":"ModuleScript","filePaths":["src/ReplicatedStorage\\Templates\\Enums.lua"]},{"name":"GameTemplate","className":"ModuleScript","filePaths":["src/ReplicatedStorage\\Templates\\GameTemplate.lua"]},{"name":"PackageTemplate","className":"ModuleScript","filePaths":["src/ReplicatedStorage\\Templates\\PackageTemplate.lua"]},{"name":"PathConfig","className":"ModuleScript","filePaths":["src/ReplicatedStorage\\Templates\\PathConfig.lua"]},{"name":"ProfileStoreTemplate","className":"ModuleScript","filePaths":["src/ReplicatedStorage\\Templates\\ProfileStoreTemplate.lua"]},{"name":"RewardTemplate","className":"ModuleScript","filePaths":["src/ReplicatedStorage\\Templates\\RewardTemplate.lua"]},{"name":"SessionDataTemplate","className":"ModuleScript","filePaths":["src/ReplicatedStorage\\Templates\\SessionDataTemplate.lua"]},{"name":"TowerTemplate","className":"ModuleScript","filePaths":["src/ReplicatedStorage\\Templates\\TowerTemplate.lua"]}]},{"name":"Utilities","className":"Folder","filePaths":["src/ReplicatedStorage\\Utilities\\init.meta.json"],"children":[{"name":"BezierPath","className":"ModuleScript","filePaths":["src/ReplicatedStorage\\Utilities\\BezierPath.lua"]},{"name":"DataModifiers","className":"ModuleScript","filePaths":["src/ReplicatedStorage\\Utilities\\DataModifiers.lua"]},{"name":"HitboxCreator","className":"ModuleScript","filePaths":["src/ReplicatedStorage\\Utilities\\HitboxCreator.lua"]},{"name":"InstanceCache","className":"ModuleScript","filePaths":["src/ReplicatedStorage\\Utilities\\InstanceCache.lua"]},{"name":"InstanceUtilities","className":"ModuleScript","filePaths":["src/ReplicatedStorage\\Utilities\\InstanceUtilities.lua"]},{"name":"QuadPath","className":"ModuleScript","filePaths":["src/ReplicatedStorage\\Utilities\\QuadPath.lua"]}]}]},{"name":"ServerScriptService","className":"ServerScriptService","children":[{"name":"Components","className":"Folder","filePaths":["src/ServerScriptService\\Components\\init.meta.json"],"children":[{"name":"AbilityComponent","className":"ModuleScript","filePaths":["src/ServerScriptService\\Components\\AbilityComponent\\init.lua"],"children":[{"name":"Fireball","className":"ModuleScript","filePaths":["src/ServerScriptService\\Components\\AbilityComponent\\Fireball.lua"]}]},{"name":"BuffsComponent","className":"ModuleScript","filePaths":["src/ServerScriptService\\Components\\BuffsComponent\\init.lua"],"children":[{"name":"BerserkersSwordBuff","className":"ModuleScript","filePaths":["src/ServerScriptService\\Components\\BuffsComponent\\BerserkersSwordBuff.lua"]},{"name":"SlownessBuff","className":"ModuleScript","filePaths":["src/ServerScriptService\\Components\\BuffsComponent\\SlownessBuff.lua"]},{"name":"TestBuff","className":"ModuleScript","filePaths":["src/ServerScriptService\\Components\\BuffsComponent\\TestBuff.lua"]},{"name":"TestBuff2","className":"ModuleScript","filePaths":["src/ServerScriptService\\Components\\BuffsComponent\\TestBuff2.lua"]}]},{"name":"EnemyComponent","className":"ModuleScript","filePaths":["src/ServerScriptService\\Components\\EnemyComponent\\init.lua"],"children":[{"name":"AbilitiesComponent","className":"ModuleScript","filePaths":["src/ServerScriptService\\Components\\EnemyComponent\\AbilitiesComponent.lua"]},{"name":"AttackComponent","className":"ModuleScript","filePaths":["src/ServerScriptService\\Components\\EnemyComponent\\AttackComponent.lua"]},{"name":"BuffComponent","className":"ModuleScript","filePaths":["src/ServerScriptService\\Components\\EnemyComponent\\BuffComponent.lua"]},{"name":"MoveComponent","className":"ModuleScript","filePaths":["src/ServerScriptService\\Components\\EnemyComponent\\MoveComponent.lua"]},{"name":"PassiveComponent","className":"ModuleScript","filePaths":["src/ServerScriptService\\Components\\EnemyComponent\\PassiveComponent.lua"]},{"name":"ValuesComponent","className":"ModuleScript","filePaths":["src/ServerScriptService\\Components\\EnemyComponent\\ValuesComponent.lua"]}]},{"name":"EnemyComponentPackage","className":"ModuleScript","filePaths":["src/ServerScriptService\\Components\\EnemyComponentPackage\\init.lua"]},{"name":"GameComponent","className":"ModuleScript","filePaths":["src/ServerScriptService\\Components\\GameComponent\\init.lua"],"children":[{"name":"WaveComponent","className":"ModuleScript","filePaths":["src/ServerScriptService\\Components\\GameComponent\\WaveComponent.lua"]}]},{"name":"LobbyComponent","className":"ModuleScript","filePaths":["src/ServerScriptService\\Components\\LobbyComponent\\init.meta.json","src/ServerScriptService\\Components\\LobbyComponent\\init.lua"]},{"name":"MovablePackageComponent","className":"ModuleScript","filePaths":["src/ServerScriptService\\Components\\MovablePackageComponent\\init.meta.json","src/ServerScriptService\\Components\\MovablePackageComponent\\init.lua"]},{"name":"PassiveComponent","className":"ModuleScript","filePaths":["src/ServerScriptService\\Components\\PassiveComponent\\init.meta.json","src/ServerScriptService\\Components\\PassiveComponent\\init.lua"],"children":[{"name":"DefaultPassives","className":"Folder","children":[{"name":"PlayerReplication","className":"ModuleScript","filePaths":["src/ServerScriptService\\Components\\PassiveComponent\\DefaultPassives\\PlayerReplication.lua"]}]},{"name":"DefaultTowerPassives","className":"Folder","children":[{"name":"TowerReplication","className":"ModuleScript","filePaths":["src/ServerScriptService\\Components\\PassiveComponent\\DefaultTowerPassives\\TowerReplication.lua"]}]},{"name":"PassiveTemplates","className":"Folder","children":[{"name":"PackagePassive","className":"ModuleScript","filePaths":["src/ServerScriptService\\Components\\PassiveComponent\\PassiveTemplates\\PackagePassive.lua"]}]},{"name":"TestPassive","className":"ModuleScript","filePaths":["src/ServerScriptService\\Components\\PassiveComponent\\TestPassive.lua"]},{"name":"TestPassive2","className":"ModuleScript","filePaths":["src/ServerScriptService\\Components\\PassiveComponent\\TestPassive2.lua"]}]},{"name":"PlayerComponent","className":"ModuleScript","filePaths":["src/ServerScriptService\\Components\\PlayerComponent\\init.lua"],"children":[{"name":"AbilitiesComponent","className":"ModuleScript","filePaths":["src/ServerScriptService\\Components\\PlayerComponent\\AbilitiesComponent.lua"]},{"name":"CharacterComponent","className":"ModuleScript","filePaths":["src/ServerScriptService\\Components\\PlayerComponent\\CharacterComponent.lua"]},{"name":"DataProfile","className":"ModuleScript","filePaths":["src/ServerScriptService\\Components\\PlayerComponent\\DataProfile.lua"]},{"name":"PartyComponent","className":"ModuleScript","filePaths":["src/ServerScriptService\\Components\\PlayerComponent\\PartyComponent.lua"]},{"name":"PassiveComponent","className":"ModuleScript","filePaths":["src/ServerScriptService\\Components\\PlayerComponent\\PassiveComponent.lua"]},{"name":"TowerComponent","className":"ModuleScript","filePaths":["src/ServerScriptService\\Components\\PlayerComponent\\TowerComponent.lua"]},{"name":"ValuesComponent","className":"ModuleScript","filePaths":["src/ServerScriptService\\Components\\PlayerComponent\\ValuesComponent.lua"]}]},{"name":"Static","className":"Folder","filePaths":["src/ServerScriptService\\Components\\Static\\init.meta.json"],"children":[{"name":"TowerAttackPatterns","className":"ModuleScript","filePaths":["src/ServerScriptService\\Components\\Static\\TowerAttackPatterns.lua"]}]},{"name":"TowerComponent","className":"ModuleScript","filePaths":["src/ServerScriptService\\Components\\TowerComponent\\init.lua"],"children":[{"name":"AbilitiesComponent","className":"ModuleScript","filePaths":["src/ServerScriptService\\Components\\TowerComponent\\AbilitiesComponent.lua"]},{"name":"AttackComponent","className":"ModuleScript","filePaths":["src/ServerScriptService\\Components\\TowerComponent\\AttackComponent.lua"]},{"name":"BuffComponent","className":"ModuleScript","filePaths":["src/ServerScriptService\\Components\\TowerComponent\\BuffComponent.lua"]},{"name":"MoveComponent","className":"ModuleScript","filePaths":["src/ServerScriptService\\Components\\TowerComponent\\MoveComponent.lua"]},{"name":"PassiveComponent","className":"ModuleScript","filePaths":["src/ServerScriptService\\Components\\TowerComponent\\PassiveComponent.lua"]},{"name":"TargetComponent","className":"ModuleScript","filePaths":["src/ServerScriptService\\Components\\TowerComponent\\TargetComponent.lua"]},{"name":"ValuesComponent","className":"ModuleScript","filePaths":["src/ServerScriptService\\Components\\TowerComponent\\ValuesComponent.lua"]}]}]},{"name":"Enemies","className":"Folder","filePaths":["src/ServerScriptService\\Enemies\\init.meta.json"],"children":[{"name":"Part","className":"ModuleScript","filePaths":["src/ServerScriptService\\Enemies\\Part.lua"]},{"name":"TowerWalker","className":"ModuleScript","filePaths":["src/ServerScriptService\\Enemies\\TowerWalker.lua"]},{"name":"Walker","className":"ModuleScript","filePaths":["src/ServerScriptService\\Enemies\\Walker.lua"]}]},{"name":"Experimental","className":"Folder","filePaths":["src/ServerScriptService\\Experimental\\init.meta.json"],"children":[{"name":"ReplicaServiceListeners","className":"ModuleScript","filePaths":["src/ServerScriptService\\Experimental\\ReplicaServiceListeners.lua"]}]},{"name":"ProfileService","className":"ModuleScript","filePaths":["src/ServerScriptService\\ProfileService.lua"]},{"name":"ReplicaService","className":"ModuleScript","filePaths":["src/ServerScriptService\\ReplicaService.lua"]},{"name":"Services","className":"Folder","filePaths":["src/ServerScriptService\\Services\\init.meta.json"],"children":[{"name":"Initializer","className":"Script","filePaths":["src/ServerScriptService\\Services\\Initializer.server.lua"]},{"name":"PackageService","className":"Script","filePaths":["src/ServerScriptService\\Services\\PackageService.server.lua"]},{"name":"PlayerService","className":"Script","filePaths":["src/ServerScriptService\\Services\\PlayerService.server.lua"]},{"name":"SignalService","className":"Script","filePaths":["src/ServerScriptService\\Services\\SignalService.server.lua"]},{"name":"TowerService","className":"Script","filePaths":["src/ServerScriptService\\Services\\TowerService.server.lua"]}]},{"name":"Towers","className":"Folder","filePaths":["src/ServerScriptService\\Towers\\init.meta.json"],"children":[{"name":"Mine","className":"ModuleScript","filePaths":["src/ServerScriptService\\Towers\\Mine.lua"]},{"name":"MovingPrecursor","className":"ModuleScript","filePaths":["src/ServerScriptService\\Towers\\MovingPrecursor.lua"]},{"name":"Precursor","className":"ModuleScript","filePaths":["src/ServerScriptService\\Towers\\Precursor.lua"]}]}]},{"name":"StarterGui","className":"StarterGui","children":[{"name":"Components","className":"Folder","filePaths":["src/StarterGui\\Components\\init.meta.json"],"children":[{"name":"UIButtonComponent","className":"ModuleScript","filePaths":["src/StarterGui\\Components\\UIButtonComponent.lua"]},{"name":"UIFrameComponent","className":"ModuleScript","filePaths":["src/StarterGui\\Components\\UIFrameComponent.lua"]}]},{"name":"UIController","className":"LocalScript","filePaths":["src/StarterGui\\UIController\\init.client.lua"],"children":[{"name":"Replication","className":"ModuleScript","filePaths":["src/StarterGui\\UIController\\Replication\\init.lua"],"children":[{"name":"HotbarController","className":"ModuleScript","filePaths":["src/StarterGui\\UIController\\Replication\\HotbarController.lua"]},{"name":"TowerController","className":"ModuleScript","filePaths":["src/StarterGui\\UIController\\Replication\\TowerController.lua"]}]}]}]},{"name":"StarterPlayer","className":"StarterPlayer","children":[{"name":"StarterPlayerScripts","className":"StarterPlayerScripts","children":[{"name":"Controllers","className":"Folder","filePaths":["src/StarterPlayer/StarterPlayerScripts\\Controllers\\init.meta.json"],"children":[{"name":"Initializer","className":"LocalScript","filePaths":["src/StarterPlayer/StarterPlayerScripts\\Controllers\\Initializer.client.lua"]},{"name":"PlayerController","className":"LocalScript","filePaths":["src/StarterPlayer/StarterPlayerScripts\\Controllers\\PlayerController.client.lua"]},{"name":"SignalController","className":"LocalScript","filePaths":["src/StarterPlayer/StarterPlayerScripts\\Controllers\\SignalController.client.lua"]}]}]}]}]}